{
  "todos": [
    {
      "id": 1660024909936,
      "title": "이중표",
      "body": "ㅁㅁㅁㅁㅁㅁㅁ",
      "time": "2022-08-09T06:01:49.936Z"
    },
    {
      "id": 1660024918315,
      "title": "이중표",
      "body": "ㅁㅁㅁㅁㅁㅁ",
      "time": "2022-08-09T06:01:58.315Z"
    },
    {
      "id": 1660024988230,
      "title": "ㅁㅇㄴㅁㄴ",
      "body": "",
      "time": "2022-08-09T06:03:08.230Z"
    },
    {
      "id": 1660046147661,
      "title": "ㅁㄴㅇㅁㄴㅇ",
      "body": "ㅁㄴㅇㅁㅇㄴ",
      "time": "2022-08-09T11:55:47.661Z"
    }
  ]
}